cryptocompy/__init__.py
cryptocompy/coin.py
cryptocompy/helper_functions.py
cryptocompy/mining.py
cryptocompy/price.py
cryptocompy/rest.py
cryptocompy/top.py
cryptocompy3-0.1.2.dist-info/METADATA
cryptocompy3-0.1.2.dist-info/RECORD
cryptocompy3-0.1.2.dist-info/WHEEL
cryptocompy3-0.1.2.dist-info/top_level.txt
